class Sigma
{
    field static int max = 100
    field static int a = 5
    field static int c
        method public static int fact(int,int)
        max_stack 15
        max_locals 15
        {
        sipush 1
        istore 2
        iload 1
        sipush 0
            isub
            ifeq L0
            iconst_0
            goto L1
        L0: iconst_1
        L1:
        ifeq L2
            sipush 1
            istore 2
            goto L3
        L2:
            iload 0
            iload 0
            sipush 1
            iadd
            iload 1
            sipush 1
            isub
            invokestatic int Sigma.fact(int,int)
            imul
            istore 2
        L3:
        iload 2
        ireturn
        }
        method public static void main(java.lang.String[])
        max_stack 15
        max_locals 15
        {
        sipush 0
        istore 0
            sipush 2
            putstatic int Sigma.c
            L4:
            getstatic int Sigma.c
            sipush 3
                isub
                ifle L5
                iconst_0
                goto L6
            L5: iconst_1
            L6:
            ifeq L7
            goto L8
            L9:
            getstatic int Sigma.c
            sipush 1
            iadd
            putstatic int Sigma.c
            goto L4
            L8:
                sipush 1
                istore 1
                iload 1
                sipush 1
                iadd
                istore 1
                getstatic java.io.PrintStream java.lang.System.out
                getstatic int Sigma.c
                invokevirtual void java.io.PrintStream.println(int)
                getstatic java.io.PrintStream java.lang.System.out
                iload 1
                invokevirtual void java.io.PrintStream.println(int)
            goto L9
            L7:
        iload 0
        sipush 5
        iadd
        istore 0
        getstatic java.io.PrintStream java.lang.System.out
        iload 0
        invokevirtual void java.io.PrintStream.println(int)
        sipush 4
        istore 1
        iload 0
        getstatic int Sigma.max
            isub
            iflt L10
            iconst_0
            goto L11
        L10: iconst_1
        L11:
        ifeq L12
            getstatic java.io.PrintStream java.lang.System.out
            sipush 2
            sipush 3
            invokestatic int Sigma.fact(int,int)
            invokevirtual void java.io.PrintStream.println(int)
            goto L13
        L12:
            getstatic java.io.PrintStream java.lang.System.out
            sipush 2
            iload 1
            invokestatic int Sigma.fact(int,int)
            invokevirtual void java.io.PrintStream.println(int)
        L13:
        iconst_0
        ifeq L14
            getstatic java.io.PrintStream java.lang.System.out
            sipush 2
            sipush 3
            invokestatic int Sigma.fact(int,int)
            invokevirtual void java.io.PrintStream.println(int)
            goto L15
        L14:
            getstatic java.io.PrintStream java.lang.System.out
            sipush 2
            iload 1
            invokestatic int Sigma.fact(int,int)
            invokevirtual void java.io.PrintStream.println(int)
        L15:
        return
        }
}
