class Sigma
{
    field static int max = 500
    field static int a = 5
    field static int c
        method public static int fact(int,int)
        max_stack 15
        max_locals 15
        {
        sipush 1
        istore 2
            iload 1
            sipush 0
                isub
                ifeq Lfact0_IF1_0
                iconst_0
                goto Lfact0_IF1_1
            Lfact0_IF1_0: iconst_1
            Lfact0_IF1_1:
            ifeq Lfact0_IF1_2
                sipush 1
                istore 2
                goto Lfact0_IF1_3
            Lfact0_IF1_2:
                iload 0
                iload 0
                sipush 1
                iadd
                iload 1
                sipush 1
                isub
                invokestatic int Sigma.fact(int,int)
                imul
                istore 2
            Lfact0_IF1_3:
        iload 2
        ireturn
        }
        method public static void main(java.lang.String[])
        max_stack 15
        max_locals 15
        {
        sipush 0
        istore 0
        iconst_1
        istore 1
        iload 1
        iconst_1
        ixor
        istore 1
        getstatic java.io.PrintStream java.lang.System.out
        iload 1
        invokevirtual void java.io.PrintStream.println(int)
            sipush 2
            putstatic int Sigma.c
            Lmain4_loop5_0:
            getstatic int Sigma.c
            sipush 3
                isub
                ifle Lmain4_loop5_1
                iconst_0
                goto Lmain4_loop5_2
            Lmain4_loop5_1: iconst_1
            Lmain4_loop5_2:
            ifeq Lmain4_loop5_3
            goto Lmain4_loop5_4
            Lmain4_loop5_5:
            getstatic int Sigma.c
            sipush 1
            iadd
            putstatic int Sigma.c
            goto Lmain4_loop5_0
            Lmain4_loop5_4:
                sipush 1
                istore 2
                iload 2
                sipush 1
                iadd
                istore 2
                sipush 1
                istore 3
                    sipush 1
                    istore 3
                    Lmain4_loop5_Compound6_loop7_3:
                    iload 3
                    sipush 3
                        isub
                        iflt Lmain4_loop5_Compound6_loop7_4
                        iconst_0
                        goto Lmain4_loop5_Compound6_loop7_5
                    Lmain4_loop5_Compound6_loop7_4: iconst_1
                    Lmain4_loop5_Compound6_loop7_5:
                    ifeq Lmain4_loop5_Compound6_loop7_6
                    goto Lmain4_loop5_Compound6_loop7_7
                    Lmain4_loop5_Compound6_loop7_8:
                    iload 3
                    sipush 1
                    iadd
                    istore 3
                    goto Lmain4_loop5_Compound6_loop7_3
                    Lmain4_loop5_Compound6_loop7_7:
                        getstatic java.io.PrintStream java.lang.System.out
                        iload 3
                        invokevirtual void java.io.PrintStream.println(int)
                    goto Lmain4_loop5_Compound6_loop7_8
                    Lmain4_loop5_Compound6_loop7_6:
                getstatic java.io.PrintStream java.lang.System.out
                ldc "======="
                invokevirtual void java.io.PrintStream.println(java.lang.String)
                    getstatic int Sigma.c
                    sipush 2
                        isub
                        ifgt Lmain4_loop5_Compound6_IF9_3
                        iconst_0
                        goto Lmain4_loop5_Compound6_IF9_4
                    Lmain4_loop5_Compound6_IF9_3: iconst_1
                    Lmain4_loop5_Compound6_IF9_4:
                    ifeq Lmain4_loop5_Compound6_IF9_5
                        getstatic java.io.PrintStream java.lang.System.out
                        ldc "test"
                        invokevirtual void java.io.PrintStream.println(java.lang.String)
                        goto Lmain4_loop5_Compound6_IF9_6
                    Lmain4_loop5_Compound6_IF9_5:
                        getstatic java.io.PrintStream java.lang.System.out
                        ldc "test2"
                        invokevirtual void java.io.PrintStream.println(java.lang.String)
                    Lmain4_loop5_Compound6_IF9_6:
                    iconst_1
                    ifeq Lmain4_loop5_Compound6_IF12_3
                        getstatic java.io.PrintStream java.lang.System.out
                        ldc "test3"
                        invokevirtual void java.io.PrintStream.println(java.lang.String)
                        goto Lmain4_loop5_Compound6_IF12_4
                    Lmain4_loop5_Compound6_IF12_3:
                        getstatic java.io.PrintStream java.lang.System.out
                        ldc "test4"
                        invokevirtual void java.io.PrintStream.println(java.lang.String)
                    Lmain4_loop5_Compound6_IF12_4:
            goto Lmain4_loop5_5
            Lmain4_loop5_3:
        iload 0
        sipush 5
        iadd
        istore 0
        getstatic java.io.PrintStream java.lang.System.out
        ldc "======="
        invokevirtual void java.io.PrintStream.println(java.lang.String)
        getstatic java.io.PrintStream java.lang.System.out
        iload 0
        invokevirtual void java.io.PrintStream.println(int)
        sipush 4
        istore 2
            iload 0
            getstatic int Sigma.max
                isub
                iflt Lmain4_IF15_0
                iconst_0
                goto Lmain4_IF15_1
            Lmain4_IF15_0: iconst_1
            Lmain4_IF15_1:
            ifeq Lmain4_IF15_2
                sipush 0
                istore 5
                    sipush 1
                    istore 5
                    Lmain4_IF15_Compound16_loop17_2:
                    iload 5
                    getstatic int Sigma.max
                        isub
                        iflt Lmain4_IF15_Compound16_loop17_3
                        iconst_0
                        goto Lmain4_IF15_Compound16_loop17_4
                    Lmain4_IF15_Compound16_loop17_3: iconst_1
                    Lmain4_IF15_Compound16_loop17_4:
                    ifeq Lmain4_IF15_Compound16_loop17_5
                    goto Lmain4_IF15_Compound16_loop17_6
                    Lmain4_IF15_Compound16_loop17_7:
                    iload 5
                    sipush 1
                    iadd
                    istore 5
                    goto Lmain4_IF15_Compound16_loop17_2
                    Lmain4_IF15_Compound16_loop17_6:
                        getstatic java.io.PrintStream java.lang.System.out
                        sipush 2
                        sipush 3
                        invokestatic int Sigma.fact(int,int)
                        invokevirtual void java.io.PrintStream.println(int)
                    goto Lmain4_IF15_Compound16_loop17_7
                    Lmain4_IF15_Compound16_loop17_5:
                    iload 5
                    sipush 2
                        isub
                        ifeq Lmain4_IF15_Compound16_IF19_2
                        iconst_0
                        goto Lmain4_IF15_Compound16_IF19_3
                    Lmain4_IF15_Compound16_IF19_2: iconst_1
                    Lmain4_IF15_Compound16_IF19_3:
                    ifeq Lmain4_IF15_Compound16_IF19_4
                        getstatic java.io.PrintStream java.lang.System.out
                        iload 5
                        invokevirtual void java.io.PrintStream.println(int)
                    Lmain4_IF15_Compound16_IF19_4:
                goto Lmain4_IF15_3
            Lmain4_IF15_2:
                getstatic java.io.PrintStream java.lang.System.out
                sipush 2
                iload 2
                invokestatic int Sigma.fact(int,int)
                invokevirtual void java.io.PrintStream.println(int)
            Lmain4_IF15_3:
        getstatic java.io.PrintStream java.lang.System.out
        ldc "======="
        invokevirtual void java.io.PrintStream.println(java.lang.String)
            iconst_0
            ifeq Lmain4_IF22_0
                getstatic java.io.PrintStream java.lang.System.out
                sipush 2
                sipush 3
                invokestatic int Sigma.fact(int,int)
                invokevirtual void java.io.PrintStream.println(int)
                goto Lmain4_IF22_1
            Lmain4_IF22_0:
                getstatic java.io.PrintStream java.lang.System.out
                sipush 2
                iload 2
                invokestatic int Sigma.fact(int,int)
                invokevirtual void java.io.PrintStream.println(int)
            Lmain4_IF22_1:
        sipush 1
        istore 3
            sipush 1
            istore 3
            Lmain4_loop25_0:
            iload 3
            sipush 3
                isub
                iflt Lmain4_loop25_1
                iconst_0
                goto Lmain4_loop25_2
            Lmain4_loop25_1: iconst_1
            Lmain4_loop25_2:
            ifeq Lmain4_loop25_3
            goto Lmain4_loop25_4
            Lmain4_loop25_5:
            iload 3
            sipush 1
            iadd
            istore 3
            goto Lmain4_loop25_0
            Lmain4_loop25_4:
                getstatic java.io.PrintStream java.lang.System.out
                iload 3
                invokevirtual void java.io.PrintStream.println(int)
            goto Lmain4_loop25_5
            Lmain4_loop25_3:
        return
        }
}
